setup.py
vrepper/__init__.py
vrepper/core.py
vrepper/version.py
vrepper/vrep.py
vrepper/vrepConst.py
vrepper.egg-info/PKG-INFO
vrepper.egg-info/SOURCES.txt
vrepper.egg-info/dependency_links.txt
vrepper.egg-info/requires.txt
vrepper.egg-info/top_level.txt