Metadata-Version: 1.1
Name: vrepper
Version: 0.0.5
Summary: V-REP python wrapper
Home-page: https://github.com/fgolemo/vrepper
Author: Florian Golemo
Author-email: fgolemo@gmail.com
License: MIT
Keywords: robotics vrep control simulation gym
Platform: UNKNOWN
Classifier: Development Status :: 4 - Beta
Classifier: Intended Audience :: Developers
Classifier: License :: OSI Approved :: MIT License
Classifier: Programming Language :: Python :: 2.7
Classifier: Programming Language :: Python :: 3.4
Classifier: Programming Language :: Python :: 3.5
Classifier: Programming Language :: Python :: 3.6
